CHANGELOG.md
CODE_OF_CONDUCT.md
CONTRIBUTING.md
LICENSE
MANIFEST.in
README.md
setup.py
doc/Makefile
doc/conf.py
doc/download-trained-networks.rst
doc/download-training-set.rst
doc/index.rst
doc/installation.rst
doc/make-training-set.rst
doc/precalculate-domain-and-range.rst
doc/requirements.txt
doc/specify-parameter-transformations.rst
doc/test-problems.rst
doc/train-networks.rst
doc/transform-training-set.rst
doc/use-networks.rst
doc/api/grtrans.rst
doc/api/impl.rst
doc/api/index.rst
neurosynchro/__init__.py
neurosynchro/cli.py
neurosynchro/grtrans.py
neurosynchro/impl.py
neurosynchro/train.py
neurosynchro.egg-info/PKG-INFO
neurosynchro.egg-info/SOURCES.txt
neurosynchro.egg-info/dependency_links.txt
neurosynchro.egg-info/entry_points.txt
neurosynchro.egg-info/requires.txt
neurosynchro.egg-info/top_level.txt